{
    "SHIPPING_ADDRESS": {
        "asistance": "bantuan",
        "addresx": "alamat",
        "uupdatte": "pembaruan",
        "addrses": "alamat",
        "hwat": "apa",
        "lelivery": "pengiriman",
        "can": "bisa",
        "unchange": "tidak berubah",
        "it": "",
        "kodinasi": "koordinasi"
    },
    "CANCELLATION_FEE": {
        "termniasi": "terminasi",
        "cancellatino": "batal",
        "earpy": "",
        "eazrly": "",
        "hwat": "apa",
        "exiut": "keluar",
        "cannott": "tidak bisa",
        "chck": "cek",
        "czncellation": "batal",
        "termimasi":"terminasi"
    },
    "PAYMENT": {
        "whee": "",
        "paymen": "pembayaran",
        "pahment": "pembayaran",
        "uaccept": "tidak terima",
        "ccan": "bisa",
        "urallowed": "tidak diizinkan",
        "cani": "bisa",
        "metos": "metode",
        "amex": "",
        "paymet": "pembayaran",
        "assisrance": "bantuan",
        "otion": "",
        "metod": "metode"
    },
    "REFUND": {
        "rabat":""
    },
    "FEEDBACK": {
        "lodge": "mengajukan",
        "helo": "",
        "lcaim": "klaim",
        "hepp": "tolong",
        "relkamasi": "reklamasi",
        "asustomer": "pelanggan",
        "commpany": "perusahaan",
        "hbelp": "tolong",
        "reclamaqtion": "reklamasi",
        "rfeclamation": "reklamasi",
        "copmlaint": "keluhan",
        "cutomer": "pelanggan",
        "clpaim": "klaim"
    },
    "CONTACT": {
        "custome": "pelanggan",
        "asistance": "bantuan",
        "uhave": "",
        "a": "",
        "address": "alamat",
        "mail": "email",
        "ohurs": "",
        "avialable": "tersedia",
        "ay": "",
        "aent": "",
        "huma": "",
        "hyman": "",
        "totalk": "berbicara",
        "uarenot": "kamu tidak",
        "live": "langsung",
        "chattinb":""
    },
    "ACCOUNT": {
        "pu": "",
        "accouint": "akun",
        "avcount": "akun",
        "onlikne": "",
        "ohw": "",
        "mwmbers": "anggota",
        "creaitng": "membuat",
        "acn": "akun",
        "assistancer": "bantuan",
        "assismatanc": "bantuan",
        "ah": "",
        "ned": "",
        "acconut": "akun",
        "accoynt": "akun",
        "clsoe": "tutup",
        "adcount": "tutup",
        "thd": "",
        "ingo": "",
        "dfata": "data",
        "moidfying": "mengubah",
        "accont": "akun",
        "thedata": "data",
        "suer": "",
        "chnage": "berubah",
        "edtail": "detail",
        "ca": "",
        "accounnt": "akun",
        "perswonal": "personal",
        "od": "",
        "edit": "mengubah",
        "passowrd": "kata sandi",
        "helpretrieving": "membantu pengambilan",
        "setel": "",
        "acecss": "akses",
        "infornasi": "informasi",
        "accpunt": "akun",
        "accesws": "akses",
        "assistanec": "bantuan",
        "uer": "",
        "inforasi": "bantuan",
        "kkey": "kunci",
        "accdss": "akses",
        "myuser": "pengguna saya",
        "olst": "",
        "accounmt": "akun",
        "uswer": "pengguna",
        "isus": "masalah",
        "issud": "masalah",
        "acxount": "akun",
        "reegistrasi": "registrasi",
        "informnig": "informasi",
        "sgnup": "mendaftar",
        "uspport": "bantuan",
        "reigstrasi": "registrasi",
        "issxues": "masalah",
        "i": "",
        "cannott": "tidak bisa",
        "goddamn": "sialan",
        "toi": "",
        "proflie": "profil",
        "hewlp": "tolong",
        "switching": "beralih",
        "howi": "bagaimana saya",
        "profle": "profil",
        "ino": "",
        "anmother": "yang lain",
        "usr": "pengguna",
        "profiole": "profil"
    },
    "NEWSLETTER": {
        "corpolrate": "korporat",
        "ur": "",
        "suscription": "langganan",
        "tbe": "",
        "corporate": "korporat",
        "nmewsletter": "buletin",
        "subscripiton": "langganan",
        "newslettee": "buletin",
        "utell": "",
        "tl": "",
        "hlp": "tolong",
        "hte": "",
        "newsleter": "buletin",
        "newslewtter": "buletin"
    }
}
